Workbook

Sheet Overview
B2: Financial-Advisory Automation Discovery MVP
B3: Chatbot-led evidence collection, ROI screening, hard control gates, and supervised-pilot planning.
B5: Workbook navigation
B7: Chatbot Playbook | C7: Questions, routes, probes and escalation
B8: Data Model | C8: Implementation-oriented logical schema
B9: Evidence Inputs | C9: Use-case, scenarios and role effort
B10: ROI Model | C10: Capacity, benefit, cost and break-even
B11: Controls & Score | C11: Prioritization, hard gates and data map
B12: Implementation Plan | C12: Architecture, delivery phases, QA and pricing
B15: Decision dashboard
B17: Selected use case | C17: ='Evidence Inputs'!C6 | E17: Expected annual released hours | F17: ='ROI Model'!D14
B18: Preliminary status | C18: ='ROI Model'!D40 | E18: Expected annual financial benefit | F18: ='ROI Model'!D25
B19: Weighted score / 100 | C19: ='Controls & Score'!E17 | E19: Expected Year-1 full cost | F19: ='ROI Model'!D29
B20: Hard-gate result | C20: ='Controls & Score'!C32 | E20: Expected Year-1 ROI | F20: ='ROI Model'!D31
B21: Evidence completeness | C21: ='Controls & Score'!E18 | E21: Expected payback (months) | F21: ='ROI Model'!D33
B24: MVP operating rules
B26: Screening, not promise | C26: The chatbot creates a bounded hypothesis and evidence plan; verified ROI follows a measured pilot.
B27: Capacity is not cash | C27: Released time is reported separately unless an accountable owner confirms a measurable economic consequence.
B28: Human accountability | C28: Named professionals approve client-facing or decision-influencing outputs.
B29: Minimum data | C29: Ordinary chat collects categories and placeholders only; approved artifacts use a separate secure channel.
B30: Hard gates override score | C30: Permission, data, verification, records and accountable-owner gates can block a high-scoring idea.
B33: Recommended sequence
B35: 1. | C35: Qualify one recurring deliverable from a recent case.
B36: 2. | C36: Measure volume, active time, review, rework, exceptions and evidence quality.
B37: 3. | C37: Gate the use against jurisdiction, data permissions, approval, records and prohibited actions.
B38: 4. | C38: Prototype bounded preparation with synthetic or redacted data.
B39: 5. | C39: Pilot with matched pre/post evidence for effort, quality, adoption, fallback and economics.
B40: 6. | C40: Deploy only after human approval of controls and value.

Sheet Chatbot Playbook
B2: Chatbot Interview Playbook
B3: One atomic question per turn; one neutral probe per topic; unknown is valid; professional and commercial decisions escalate to humans.
B5: Route | C5: ID | D5: State | E5: Question / action | F5: Captured field | G5: Required | H5: Probe trigger | I5: Neutral probe / controls | J5: Escalate when
B6: Universal | C6: U0 | D6: Disclosure | E6: Disclose automation, transcript, purpose, access, retention, prohibited data, skip/stop rights, and preliminary status. | F6: notice_version | G6: Yes | I6: Affirmative consent / decline | J6: Consent or retention disputed
B7: Universal | C7: U1 | D7: Consent | E7: Do you agree to continue under the notice? | F7: consent | G7: Yes | I7: Yes / No | J7: No consent
B8: Universal | C8: U2 | D8: Role | E8: Which perspective best matches your role? | F8: respondent_role | G8: Yes | I8: Adviser; Operations; Compliance; Finance; Multiple; Unsure | J8: Authority cannot be established
B9: Universal | C9: U3 | D9: Evidence | E9: Are you answering from direct experience, oversight, or both? | F9: authority_level | G9: Yes | I9: Direct; Oversight; Both
B10: Adviser | C10: A1 | D10: Candidate | E10: Think of the most recent normal recurring work you would like made easier. What final item did you deliver? | F10: deliverable | G10: Yes | H10: Broad or several candidates | I10: What specific item was complete at the end? | J10: No bounded output
B11: Adviser | C11: A2 | D11: Outcome | E11: Who used that item? | F11: recipient | G11: Yes | H11: Recipient unclear | I11: Which role or client type received it? | J11: No user
B12: Adviser | C12: A3 | D12: Outcome | E12: What did it allow that person to decide or do? | F12: outcome | G12: Yes | H12: Outcome vague | I12: What changed after acceptance? | J12: No outcome
B13: Adviser | C13: A4 | D13: Volume | E13: In the last full normal month, approximately how many similar items were completed? | F13: monthly_volume | G13: Yes | H13: No unit/source | I13: Provide a value or range and the source.
B14: Adviser | C14: A5 | D14: Economics | E14: How does this work affect the business financially? | F14: value_mechanism | G14: Yes | H14: Generic productivity | I14: What spend, margin, obligation or capacity consequence changes? | J14: Only unspecified time saved
B15: Adviser | C15: A6 | D15: Capacity | E15: If preparation used less staff time, what would actually change within 12 months? | F15: capacity_use | G15: Yes | H15: No realization path | I15: Spend stops; hiring avoided; demand served; backlog cleared; capacity only? | J15: No value path
B16: Adviser | C16: A7 | D16: Owner | E16: Who can verify volume, economics and the intended use of capacity? | F16: evidence_owner | G16: Yes | H16: Owner unknown | I16: Which role controls the record or budget? | J16: No owner
B17: Adviser | C17: A8 | D17: Trust | E17: What is the highest assistance level you would consider? | F17: trust_boundary | G17: Yes | I17: Organize; Draft; Recommend for approval; Reversible internal action; External action; Unsure | J17: External advice/action without approval
B18: Operations | C18: O1 | D18: Case | E18: Was the most recent example normal, unusually easy, or difficult? | F18: case_typicality | G18: Yes | I18: Normal; Easy; Difficult
B19: Operations | C19: O2 | D19: Boundary | E19: What event started the work? | F19: start_event | G19: Yes | H19: Unclear boundary | I19: What first event triggered active work?
B20: Operations | C20: O3 | D20: Boundary | E20: What event meant the item was accepted as complete? | F20: finish_event | G20: Yes | H20: Acceptance unclear | I20: Who accepted it or what status marked completion? | J20: No acceptance standard
B21: Operations | C21: O4 | D21: Roles | E21: Which roles spent active time on the example? | F21: roles | G21: Yes | I21: Roles only; no employee names.
B22: Operations | C22: O5 | D22: Time | E22: How much active time did each role spend, excluding waiting? | F22: baseline_time | G22: Yes | H22: No unit/source | I22: Give a value/range and source: record, timestamp, diary, file history or memory. | J22: Baseline unmeasurable
B23: Operations | C23: O6 | D23: Review | E23: How much extra active time followed for review or correction? | F23: review_time | G23: Yes | H23: Combined with creation | I23: Separate verification and correction if possible.
B24: Operations | C24: O7 | D24: Exceptions | E24: Out of ten similar items, how many needed materially different handling? | F24: exception_rate | G24: No | H24: Material unclear | I24: Material means meaningful extra work or changed client conclusion.
B25: Operations | C25: O8 | D25: Quality | E25: What must not become worse? | F25: quality_guardrail | G25: Yes | H25: Not measurable | I25: How is it checked today? | J25: No verification method
B26: Operations | C26: O9 | D26: Evidence | E26: Which record could verify volume, effort or rework with least effort? | F26: baseline_evidence | G26: Yes | H26: No record | I26: Could a diary of 5–10 normal cases work? | J26: No evidence path
B27: Compliance | C27: C1 | D27: Perimeter | E27: Which country, entity and regulated activity would this use touch? | F27: perimeter | G27: Yes | H27: Incomplete | I27: Name the responsible firm role. | J27: Legal interpretation requested
B28: Compliance | C28: C2 | D28: Class | E28: How does the firm classify the output? | F28: output_class | G28: Yes | I28: Preparation; Communication; Advice; Record; Supervision; Other | J28: Advice without professional approval
B29: Compliance | C29: C3 | D29: Data | E29: Which data categories are minimally required? | F29: data_categories | G29: Yes | H29: Sensitive content entered | I29: Restate with categories/placeholders. | J29: Credentials or identifiable records
B30: Compliance | C30: C4 | D30: Pilot data | E30: What is the least sensitive permitted pilot data? | F30: pilot_data | G30: Yes | I30: Synthetic; Redacted; Anonymized; Historical; Controlled live; None | J30: No permissible path
B31: Compliance | C31: C5 | D31: Prohibition | E31: What must the automation never access, generate, decide or send? | F31: prohibited_actions | G31: Yes | H31: Unclear | J31: Possible breach/control failure
B32: Compliance | C32: C6 | D32: Approval | E32: Which qualified role approves output before use or sending? | F32: human_approver | G32: Yes | H32: No reviewer | I32: What qualification is required? | J32: No competent reviewer
B33: Compliance | C33: C7 | D33: Records | E33: Which prompts, inputs, outputs, approvals, versions and actions must be retained? | F33: record_requirements | G33: Yes | H33: Unknown | I33: Who defines retention/deletion? | J33: Recordkeeping unmet
B34: Compliance | C34: C8 | D34: Authority | E34: Who authorizes a limited pilot, and what evidence is required? | F34: pilot_authority | G34: Yes | H34: Unknown | J34: Permission claims conflict
B35: Finance | C35: F1 | D35: Cost | E35: Which approved loaded cost basis applies to each role? | F35: loaded_cost | G35: Yes | H35: Unavailable | I35: Finance-approved hourly or standard basis.
B36: Finance | C36: F2 | D36: Spend | E36: Which current or planned expenditure would change? | F36: spend_change | G36: No | H36: Uncommitted | I36: Name budget line, owner, amount and timing.
B37: Finance | C37: F3 | D37: Growth | E37: Is there evidenced demand, and what contribution margin applies? | F37: growth_economics | G37: No | H37: Uses revenue | I37: Use attributable contribution margin, not revenue.
B38: Finance | C38: F4 | D38: Appraisal | E38: What horizon and payback rule should apply? | F38: appraisal_rule | G38: Yes | J38: Binding commitment requested
B39: Universal | C39: U4 | D39: Correction | E39: Review facts, estimates, interpretations and unknowns. What should be corrected or qualified? | F39: corrections | G39: Yes | I39: Free text or No corrections.
B40: Universal | C40: U5 | D40: Validation | E40: Which single assumption should be validated first? | F40: priority_assumption | G40: Yes | I40: Largest value or safety uncertainty.
B41: Universal | C41: U6 | D41: Handoff | E41: Classify Stop, Measure, Prototype or Pilot and create a human-review brief. | F41: next_step | G41: Yes | I41: Human review required = true | J41: Any legal, incident, advice, permission or commercial decision

Sheet Data Model
B2: MVP Data Model
B3: Logical schema supporting interview state, provenance, ROI, controls, agent identities and pilot measurement.
B5: Entity | C5: Field | D5: Type | E5: Required | F5: Definition / values | G5: Source owner | H5: Sensitivity | I5: Validation rule
B6: Organization | C6: organization_id | D6: UUID | E6: Yes | F6: Primary key | G6: System | H6: Internal | I6: Unique
B7: Organization | C7: jurisdiction | D7: Text | E7: Yes | F7: Country and regulatory perimeter | G7: Compliance | H7: Internal | I7: Must be confirmed
B8: InterviewSession | C8: session_id | D8: UUID | E8: Yes | F8: Session key | G8: System | H8: Internal | I8: Unique
B9: InterviewSession | C9: notice_version | D9: Text | E9: Yes | F9: Approved notice version | G9: System | H9: Internal | I9: Before consent
B10: InterviewSession | C10: consent_status | D10: Enum | E10: Yes | F10: Accepted; Declined; Withdrawn | G10: Respondent | H10: Personal | I10: No interview unless accepted
B11: InterviewSession | C11: state | D11: Enum | E11: Yes | F11: Disclosure through Handoff | G11: System | H11: Internal | I11: Deterministic
B12: InterviewSession | C12: questionnaire_model_versions | D12: Text | E12: Yes | F12: Questionnaire, prompt, model and tool versions | G12: System | H12: Internal | I12: Immutable per session
B13: Respondent | C13: role_authority | D13: Enum | E13: Yes | F13: Role plus direct/oversight/both | G13: Respondent | H13: Internal | I13: Required provenance
B14: UseCase | C14: deliverable_name | D14: Text | E14: Yes | F14: One bounded recurring output | G14: Adviser | H14: Internal | I14: Reject broad process
B15: UseCase | C15: recipient_outcome | D15: Text | E15: Yes | F15: User and enabled decision/action | G15: Adviser | H15: Internal | I15: Required
B16: UseCase | C16: start_finish_events | D16: Text | E16: Yes | F16: Observable measurement boundary | G16: Operations | H16: Internal | I16: Accepted finish
... B35: PilotMetric | C35: type_baseline_pilot_threshold | D35: Variant | E35: Yes | F35: Matched pre/post metric and acceptance threshold | G35: Pilot owner | H35: Internal | I35: Deployment-like evidence

Sheet Evidence Inputs
B2: Evidence Inputs
B3: Yellow cells are client/project inputs. Store ranges and provenance; do not replace unknowns with invented values.
B4: Use-case identity and governance
B6: Use case name | G6: Short bounded label
B7: Firm / entity | G7: Legal entity
B8: Jurisdiction | G8: Actual perimeter
B9: Recurring deliverable | G9: Concrete artifact/result
B10: Recipient / user | G10: Role or client type
B11: Start event | G11: Observable trigger
B12: Accepted completion | G12: Observable acceptance
B13: Value mechanism | G13: Cash; avoidance; margin; quality/risk; capacity
B14: Human approver | G14: Qualified role
B15: Pilot data class | G15: Least sensitive permitted variant
B16: Business owner | G16: Accountable sponsor
B19: Scenario assumptions
B21: Key | C21: Input | D21: Low | E21: Expected | F21: High | G21: Unit | H21: Grade | I21: Source role | J21: Evidence type | K21: Validation owner | L21: Notes
B22: monthly_volume | C22: Cases per normal month | G22: cases/month
B23: eligible_share | C23: Eligible share | G23: %
B24: adoption | C24: Sustained adoption | G24: %
B25: capacity_realization | C25: Capacity realization factor (informational) | G25: %
B26: cash_savings | C26: Confirmed annual cash saving | G26: $ / year
B27: cost_avoidance | C27: Evidenced annual cost avoidance | G27: $ / year
B28: incremental_cases_month | C28: Additional paid cases/month | G28: cases/month
B29: contribution_margin_case | C29: Contribution margin/additional case | G29: $ / case
B30: quality_benefit | C30: Monetized annual quality benefit | G30: $ / year
B31: current_risk_probability | C31: Current loss-event probability | G31: %
B32: residual_risk_probability | C32: Residual loss-event probability | G32: %
B33: risk_loss_impact | C33: Impact per loss event | G33: $ / event
... B40: appraisal_years | C40: Appraisal horizon | G40: years
B43: Role effort per accepted case
B45: Role | C45: Baseline hrs Low | D45: Baseline hrs Expected | E45: Baseline hrs High | F45: Assisted hrs Low | G45: Assisted hrs Expected | H45: Assisted hrs High | I45: Cost/hr Low | J45: Cost/hr Expected | K45: Cost/hr High | L45: Grade | M45: Source / notes
B56: Evidence grades: A system/ledger/approved finance; B recent sample/timestamp/diary; C reconciled estimates; D unsupported recollection; E automation-team assumption. Grade E is never client evidence.

Sheet ROI Model
B2: Preliminary ROI Model
B3: Dynamic low / expected / high screening model; financial ROI excludes released-capacity equivalents unless independently evidenced.
B5: Metric | C5: Low | D5: Expected | E5: High | F5: Interpretation
B7: Annual total cases | C7: =IF('Evidence Inputs'!D22="","",'Evidence Inputs'!D22*12) | D7: =IF('Evidence Inputs'!E22="","",'Evidence Inputs'!E22*12) | E7: =IF('Evidence Inputs'!F22="","",'Evidence Inputs'!F22*12) | F7: Monthly volume × 12
B8: Eligible cases | C8: =IF(OR(C7="",'Evidence Inputs'!D23=""),"",C7*'Evidence Inputs'!D23) | D8: =IF(OR(D7="",'Evidence Inputs'!E23=""),"",D7*'Evidence Inputs'!E23) | E8: =IF(OR(E7="",'Evidence Inputs'!F23=""),"",E7*'Evidence Inputs'!F23) | F8: Annual cases × eligible share
B9: Adopted cases | C9: =IF(OR(C8="",'Evidence Inputs'!D24=""),"",C8*'Evidence Inputs'!D24) | D9: =IF(OR(D8="",'Evidence Inputs'!E24=""),"",D8*'Evidence Inputs'!E24) | E9: =IF(OR(E8="",'Evidence Inputs'!F24=""),"",E8*'Evidence Inputs'!F24) | F9: Eligible × adoption
B11: Baseline active hours / case | C11: =IF(COUNTA('Evidence Inputs'!$C$46:$C$53)=0,"",SUM('Evidence Inputs'!$C$46:$C$53)) | D11: =IF(COUNTA('Evidence Inputs'!$D$46:$D$53)=0,"",SUM('Evidence Inputs'!$D$46:$D$53)) | E11: =IF(COUNTA('Evidence Inputs'!$E$46:$E$53)=0,"",SUM('Evidence Inputs'!$E$46:$E$53)) | F11: Sum by role
B12: Assisted active hours / case | C12: =IF(COUNTA('Evidence Inputs'!$F$46:$F$53)=0,"",SUM('Evidence Inputs'!$F$46:$F$53)) | D12: =IF(COUNTA('Evidence Inputs'!$G$46:$G$53)=0,"",SUM('Evidence Inputs'!$G$46:$G$53)) | E12: =IF(COUNTA('Evidence Inputs'!$H$46:$H$53)=0,"",SUM('Evidence Inputs'!$H$46:$H$53)) | F12: Pilot hypothesis/measurement including review
B13: Net released hours / case | C13: =IF(OR(C11="",C12=""),"",MAX(0,C11-C12)) | D13: =IF(OR(D11="",D12=""),"",MAX(0,D11-D12)) | E13: =IF(OR(E11="",E12=""),"",MAX(0,E11-E12)) | F13: Never below zero
B14: Annual released capacity hours | C14: =IF(OR(C9="",C13=""),"",C9*C13) | D14: =IF(OR(D9="",D13=""),"",D9*D13) | E14: =IF(OR(E9="",E13=""),"",E9*E13) | F14: Capacity, not cash
B15: Baseline labour cost / case | C15: =IF(COUNTA('Evidence Inputs'!$C$46:$C$53)=0,"",SUMPRODUCT('Evidence Inputs'!$C$46:$C$53,'Evidence Inputs'!$I$46:$I$53)) | D15: =IF(COUNTA('Evidence Inputs'!$D$46:$D$53)=0,"",SUMPRODUCT('Evidence Inputs'!$D$46:$D$53,'Evidence Inputs'!$J$46:$J$53)) | E15: =IF(COUNTA('Evidence Inputs'!$E$46:$E$53)=0,"",SUMPRODUCT('Evidence Inputs'!$E$46:$E$53,'Evidence Inputs'!$K$46:$K$53)) | F15: Loaded-cost equivalent
B16: Assisted labour cost / case | C16: =IF(COUNTA('Evidence Inputs'!$F$46:$F$53)=0,"",SUMPRODUCT('Evidence Inputs'!$F$46:$F$53,'Evidence Inputs'!$I$46:$I$53)) | D16: =IF(COUNTA('Evidence Inputs'!$G$46:$G$53)=0,"",SUMPRODUCT('Evidence Inputs'!$G$46:$G$53,'Evidence Inputs'!$J$46:$J$53)) | E16: =IF(COUNTA('Evidence Inputs'!$H$46:$H$53)=0,"",SUMPRODUCT('Evidence Inputs'!$H$46:$H$53,'Evidence Inputs'!$K$46:$K$53)) | F16: Loaded-cost equivalent
B17: Gross labour capacity equivalent | C17: =IF(OR(C9="",C15="",C16=""),"",C9*MAX(0,C15-C16)) | D17: =IF(OR(D9="",D15="",D16=""),"",D9*MAX(0,D15-D16)) | E17: =IF(OR(E9="",E15="",E16=""),"",E9*MAX(0,E15-E16)) | F17: Not financial ROI
B18: Realizable capacity equivalent | C18: =IF(OR(C17="",'Evidence Inputs'!D25=""),"",C17*'Evidence Inputs'!D25) | D18: =IF(OR(D17="",'Evidence Inputs'!E25=""),"",D17*'Evidence Inputs'!E25) | E18: =IF(OR(E17="",'Evidence Inputs'!F25=""),"",E17*'Evidence Inputs'!F25) | F18: Informational until economic consequence evidenced
B20: Confirmed cash saving | C20: =IF('Evidence Inputs'!D26="","",'Evidence Inputs'!D26) | D20: =IF('Evidence Inputs'!E26="","",'Evidence Inputs'!E26) | E20: =IF('Evidence Inputs'!F26="","",'Evidence Inputs'!F26) | F20: Finance-owned
B21: Evidenced cost avoidance | C21: =IF('Evidence Inputs'!D27="","",'Evidence Inputs'!D27) | D21: =IF('Evidence Inputs'!E27="","",'Evidence Inputs'!E27) | E21: =IF('Evidence Inputs'!F27="","",'Evidence Inputs'!F27) | F21: Finance-owned
B22: Incremental contribution margin | C22: =IF(OR('Evidence Inputs'!D28="",'Evidence Inputs'!D29=""),"",'Evidence Inputs'!D28*12*'Evidence Inputs'!D29) | D22: =IF(OR('Evidence Inputs'!E28="",'Evidence Inputs'!E29=""),"",'Evidence Inputs'!E28*12*'Evidence Inputs'!E29) | E22: =IF(OR('Evidence Inputs'!F28="",'Evidence Inputs'!F29=""),"",'Evidence Inputs'!F28*12*'Evidence Inputs'!F29) | F22: Not revenue
B23: Monetized quality benefit | C23: =IF('Evidence Inputs'!D30="","",'Evidence Inputs'!D30) | D23: =IF('Evidence Inputs'!E30="","",'Evidence Inputs'!E30) | E23: =IF('Evidence Inputs'!F30="","",'Evidence Inputs'!F30) | F23: Only defensible linkage
B24: Expected risk reduction | C24: =IF(OR('Evidence Inputs'!D31="",'Evidence Inputs'!D32="",'Evidence Inputs'!D33=""),"",MAX(0,'Evidence Inputs'!D31-'Evidence Inputs'!D32)*'Evidence Inputs'!D33) | D24: =IF(OR('Evidence Inputs'!E31="",'Evidence Inputs'!E32="",'Evidence Inputs'!E33=""),"",MAX(0,'Evidence Inputs'!E31-'Evidence Inputs'!E32)*'Evidence Inputs'!E33) | E24: =IF(OR('Evidence Inputs'!F31="",'Evidence Inputs'!F32="",'Evidence Inputs'!F33=""),"",MAX(0,'Evidence Inputs'!F31-'Evidence Inputs'!F32)*'Evidence Inputs'!F33) | F24: Probability change × impact
B25: Annual financial benefit | C25: =IF(COUNT(C20:C24)=0,"",SUM(C20:C24)) | D25: =IF(COUNT(D20:D24)=0,"",SUM(D20:D24)) | E25: =IF(COUNT(E20:E24)=0,"",SUM(E20:E24)) | F25: Sum of evidenced benefits
B27: One-time implementation cost | C27: =IF(COUNT('Evidence Inputs'!D34,'Evidence Inputs'!D35)=0,"",SUM('Evidence Inputs'!D34,'Evidence Inputs'!D35)) | D27: =IF(COUNT('Evidence Inputs'!E34,'Evidence Inputs'!E35)=0,"",SUM('Evidence Inputs'!E34,'Evidence Inputs'!E35)) | E27: =IF(COUNT('Evidence Inputs'!F34,'Evidence Inputs'!F35)=0,"",SUM('Evidence Inputs'!F34,'Evidence Inputs'!F35)) | F27: External + internal
B28: Annual recurring full cost | C28: =IF(COUNT('Evidence Inputs'!D36,'Evidence Inputs'!D37,'Evidence Inputs'!D38)=0,"",SUM('Evidence Inputs'!D36,'Evidence Inputs'!D37,'Evidence Inputs'!D38)) | D28: =IF(COUNT('Evidence Inputs'!E36,'Evidence Inputs'!E37,'Evidence Inputs'!E38)=0,"",SUM('Evidence Inputs'!E36,'Evidence Inputs'!E37,'Evidence Inputs'!E38)) | E28: =IF(COUNT('Evidence Inputs'!F36,'Evidence Inputs'!F37,'Evidence Inputs'!F38)=0,"",SUM('Evidence Inputs'!F36,'Evidence Inputs'!F37,'Evidence Inputs'!F38)) | F28: Platform + maintenance + oversight
B29: Year-1 full cost | C29: =IF(OR(C27="",C28=""),"",C27+C28) | D29: =IF(OR(D27="",D28=""),"",D27+D28) | E29: =IF(OR(E27="",E28=""),"",E27+E28) | F29: One-time + recurring
B30: Year-1 net benefit | C30: =IF(OR(C25="",C29=""),"",C25-C29) | D30: =IF(OR(D25="",D29=""),"",D25-D29) | E30: =IF(OR(E25="",E29=""),"",E25-E29) | F30: Benefit − cost
B31: Year-1 ROI | C31: =IF(OR(C29="",C29=0,C25=""),"",(C25-C29)/C29) | D31: =IF(OR(D29="",D29=0,D25=""),"",(D25-D29)/D29) | E31: =IF(OR(E29="",E29=0,E25=""),"",(E25-E29)/E29) | F31: Net benefit / cost
B32: Recurring annual net benefit | C32: =IF(OR(C25="",C28=""),"",C25-C28) | D32: =IF(OR(D25="",D28=""),"",D25-D28) | E32: =IF(OR(E25="",E28=""),"",E25-E28) | F32: Benefit − recurring cost
B33: Payback period (months) | C33: =IF(OR(C27="",C32<=0),"",C27/C32*12) | D33: =IF(OR(D27="",D32<=0),"",D27/D32*12) | E33: =IF(OR(E27="",E32<=0),"",E27/E32*12) | F33: One-time / recurring net benefit
B34: Three-year full cost | C34: =IF(OR(C27="",C28=""),"",C27+3*C28) | D34: =IF(OR(D27="",D28=""),"",D27+3*D28) | E34: =IF(OR(E27="",E28=""),"",E27+3*E28) | F34: One-time + 3× recurring
B35: Three-year ROI | C35: =IF(OR(C34="",C34=0,C25=""),"",(3*C25-C34)/C34) | D35: =IF(OR(D34="",D34=0,D25=""),"",(3*D25-D34)/D34) | E35: =IF(OR(E34="",E34=0,E25=""),"",(3*E25-E34)/E34) | F35: 3-year benefit vs cost
B36: Maximum affordable Year-1 cost | C36: =IF(C25="","",C25) | D36: =IF(D25="","",D25) | E36: =IF(E25="","",E25) | F36: Benefit at break-even
B38: Extra paid cases/month for break-even | C38: =IF(OR('Evidence Inputs'!D29="",'Evidence Inputs'!D29=0,C29=""),"",MAX(0,C29-SUM(C20,C21,C23,C24))/'Evidence Inputs'!D29/12) | D38: =IF(OR('Evidence Inputs'!E29="",'Evidence Inputs'!E29=0,D29=""),"",MAX(0,D29-SUM(D20,D21,D23,D24))/'Evidence Inputs'!E29/12) | E38: =IF(OR('Evidence Inputs'!F29="",'Evidence Inputs'!F29=0,E29=""),"",MAX(0,E29-SUM(E20,E21,E23,E24))/'Evidence Inputs'!F29/12) | F38: Residual cost / margin / 12
B40: Screening status | C40: =IF(OR(C7="",C11="",C12="",C29=""),"Incomplete — validate baseline and cost",IF(C25="","Operational case only",IF(C31>0,"Positive preliminary case — pilot required","Not yet positive — measure/redesign"))) | D40: =IF(OR(D7="",D11="",D12="",D29=""),"Incomplete — validate baseline and cost",IF(D25="","Operational case only",IF(D31>0,"Positive preliminary case — pilot required","Not yet positive — measure/redesign"))) | E40: =IF(OR(E7="",E11="",E12="",E29=""),"Incomplete — validate baseline and cost",IF(E25="","Operational case only",IF(E31>0,"Positive preliminary case — pilot required","Not yet positive — measure/redesign"))) | F40: Preliminary; human review required
B43: Screening only: replace interview assumptions with matched pilot evidence for active time, review, correction, exceptions, adoption, fallback, quality, economic consequence and full cost.

Sheet Controls & Score
B2: Controls, Scorecard and Data Map
B3: A weighted score prioritizes; hard gates decide whether the work can proceed.
B5: Candidate scorecard
B7: Criterion | C7: Weight | D7: Score 1–5 | E7: Weighted points | F7: Evidence | G7: Blocking rule
B8: Material value | C8: 0.2 | E8: =IF(D8="","",D8/5*C8*100) | G8: No outcome means no recommendation
B9: Frequency / volume | C9: 0.1 | E9: =IF(D9="","",D9/5*C9*100) | G9: Low volume needs high unit value
B10: Standardization | C10: 0.1 | E10: =IF(D10="","",D10/5*C10*100) | G10: Unstable output favors measurement
B11: Data readiness | C11: 0.15 | E11: =IF(D11="","",D11/5*C11*100) | G11: Unclear permission blocks live data
B12: Reviewability | C12: 0.1 | E12: =IF(D12="","",D12/5*C12*100) | G12: No verifier blocks high impact
B13: Technical feasibility | C13: 0.1 | E13: =IF(D13="","",D13/5*C13*100) | G13: Unknown integration remains discovery
B14: Adoption | C14: 0.1 | E14: =IF(D14="","",D14/5*C14*100) | G14: No user/owner blocks rollout
B15: Value realization | C15: 0.1 | E15: =IF(D15="","",D15/5*C15*100) | G15: No capacity use weakens ROI
B16: Risk manageability | C16: 0.05 | E16: =IF(D16="","",D16/5*C16*100) | G16: Compliance veto overrides score
B17: Weighted score / 100 | E17: =IF(COUNT(D8:D16)<9,"",SUM(E8:E16))
B18: Evidence completeness | E18: =COUNT(D8:D16)/9
B21: Hard gates
B23: Gate | C23: Requirement | D23: Status | E23: Owner | F23: Evidence / action | G23: Impact
B24: Bounded recurring unit | C24: Start, finish, user and outcome | G24: Fail/unknown limits or blocks progress
B25: Permissible data path | C25: Authorized pilot-data option | G25: Fail/unknown limits or blocks progress
B26: Qualified reviewer | C26: Competent case-level verification | G26: Fail/unknown limits or blocks progress
B27: Legal / contractual permission | C27: Responsible firm confirmation | G27: Fail/unknown limits or blocks progress
B28: Verification method | C28: Baseline and quality measurable | G28: Fail/unknown limits or blocks progress
B29: Accountable owners | C29: Business, control and pilot owners | G29: Fail/unknown limits or blocks progress
B30: Records / audit trail | C30: Required prompts, outputs, approvals, versions and actions retained | G30: Fail/unknown limits or blocks progress
B32: Hard-gate result | C32: =IF(COUNTIF(D24:D30,"Fail")>0,"BLOCKED",IF(COUNTIF(D24:D30,"Pass")=7,"PASS","INCOMPLETE"))
B35: Minimum viable data map
B37: Data category | C37: Purpose | D37: Source system | E37: Sensitivity | F37: Permission | G37: Storage/region | H37: Retention/deletion | I37: Human access | J37: Agent access | K37: Status

Sheet Implementation Plan
B2: MVP Implementation Plan
B3: Governed architecture, staged delivery, QA, pilot measures and commercial structure.
B5: Target architecture
B7: Component | C7: Purpose | D7: MVP boundary | E7: Key control | F7: Owner | G7: Acceptance evidence
B8: Chat interface | C8: Consent, routing, questions, progress, pause | D8: Text only; no live documents | E8: Privacy warning and interruption | F8: Product | G8: Transcript tests
B9: Orchestrator | C9: State, probes, completion and escalation | D9: Four role routes and handoff | E9: No silent inference | F9: Engineering | G9: State tests
B10: Evidence registry | C10: Values, ranges and provenance | D10: Structured use-case records | E10: Immutable source/grade | F10: Data | G10: Schema audit
B11: ROI engine | C11: Capacity, benefit, cost, break-even | D11: Preliminary scenarios | E11: Capacity separated from ROI | F11: Finance/Product | G11: Formula reconciliation
B12: Control gate | C12: Approvals, prohibitions and status | D12: Pilot gate, not legal opinion | E12: Veto overrides score | F12: Compliance | G12: Signed gate record
B13: Secure artifacts | C13: Approved redacted evidence | D13: Separate authorized flow | E13: Purpose/viewers/retention | F13: Security | G13: Upload/deletion test
B14: Agent workspace | C14: Named agent users and tasks | D14: Bounded preparation only | E14: Least privilege and approvals | F14: Platform | G14: Access tests
B15: System connector | C15: Approved API/UI integration | D15: One pilot system | E15: Scoped account, reversible actions | F15: Engineering | G15: Integration test
B16: Audit/monitoring | C16: Versions, outputs, actions, overrides, incidents | D16: Pilot dashboard/export | E16: Retention and review cadence | F16: Compliance/Ops | G16: Audit sample
B19: Delivery phases
B21: Phase | C21: Span | D21: Main work | E21: Exit deliverable | F21: Decision gate | G21: Owners
B22: 0 Governance | C22: Week 0–1 | D22: Notice, retention, prohibited data, escalation, owners, perimeter | E22: Approved policy/data flow | F22: No collection before approval | G22: Sponsor; Compliance; Security
B23: 1 Configure MVP | C23: Week 1–3 | D23: Routes, schema, evidence, formulas, access, versioning | E23: Testable MVP | F23: Design review | G23: Product; Engineering; Data
B24: 2 Pre-release QA | C24: Week 3–4 | D24: Adversarial privacy, branching, extraction, escalation and formula tests | E24: QA report | F24: Control sign-off | G24: QA; Compliance; Security
B25: 3 Discovery alpha | C25: Week 5 | D25: Internal/low-risk sessions without production client data | E25: Structured handoffs | F25: Fidelity accepted | G25: Product; SME
B26: 4 Client discovery | C26: Week 6 | D26: Targeted adviser, operations, compliance and finance routes | E26: Bounded candidate/gaps | F26: Stop / Measure / Prototype | G26: Client owners
B27: 5 Measurement sprint | C27: Week 6–8 | D27: Sample 5–10 normal cases | E27: Validated baseline | F27: Evidence sufficient | G27: Operations; Data
B28: 6 Prototype | C28: Week 8–10 | D28: Synthetic/redacted preparation test | E28: Technical/control evidence | F28: Guardrails pass | G28: Engineering; Compliance
B29: 7 Supervised pilot | C29: Week 10–12+ | D29: Matched pre/post in deployment-like conditions | E29: Measured economics and quality | F29: Deploy / revise / stop | G29: Business; Compliance; Finance
B30: 8 Production | C30: After approval | D30: Harden access, monitoring, support and change control | E30: Release package | F30: Formal go/no-go | G30: Executive/control owners
B33: Pilot measures
B35: Measure | C35: Logic | D35: Evidence | E35: Stop / guardrail | F35: Owner | G35: Cadence
B36: Eligible volume | C36: Same definition before/after | D36: Queue/system count | E36: Scope drift invalidates comparison | F36: Operations | G36: Weekly
B37: Human time | C37: Creation + review + correction + fallback | D37: Timestamps/diary/task record | E37: Do not omit verification/exceptions | F37: Operations | G37: Per case
B38: Quality/severity | C38: Correctness, completeness, compliance, traceability, timeliness | D38: Reviewer checklist/defect log | E38: Material unsafe error pauses pilot | F38: Qualified reviewer | G38: Every initial case
B39: Adoption | C39: Eligible cases processed and bypass reasons | D39: Usage/abandonment log | E39: Low sustained use weakens value | F39: Product | G39: Weekly
B40: Overrides | C40: Changes, rejection and reasons | D40: Approval/action log | E40: Repeated critical override redesigns | F40: Compliance | G40: Weekly
B41: Economics | C41: Stopped spend, avoided plan, margin or loss reduction | D41: Finance record | E41: Capacity alone is not ROI | F41: Finance | G41: Monthly
B42: Incidents | C42: Disclosure, access or leakage | D42: Incident register | E42: Serious incident stops pilot | F42: Security/Compliance | G42: Continuous
B43: Changes | C43: Prompt, model, tool and route versions | D43: Change log | E43: Material change retested | F43: Engineering/QA | G43: Each release
B46: Commercial model
B48: Discovery/measurement | C48: Fixed fee for assessment, evidence plan and baseline sprint. | F48: No promised ROI.
B49: Implementation | C49: Milestone fee by deliverable family and bounded scope. | F49: Include data, integration, controls, testing and training.
B50: Recurring service | C50: Platform, hosting, monitoring, support, maintenance, review and governance. | F50: Tie scope to service levels and control duties.
B51: Outcome-linked option | C51: Only with attributable baseline, finance owner and contractual measurement. | F51: Never price from ambiguous time saved.
